kriten/__init__.py
kriten/filtersets.py
kriten/forms.py
kriten/models.py
kriten/navigation.py
kriten/services.py
kriten/tables.py
kriten/urls.py
kriten/views.py
kriten/api/__init__.py
kriten/api/serializers.py
kriten/api/urls.py
kriten/api/views.py
kriten/migrations/0001_initial.py
kriten/migrations/0002_alter_kritentask_kriten_cluster.py
kriten/migrations/0003_kritenjob.py
kriten/migrations/0004_alter_kritenjob_completed_and_more.py
kriten/migrations/0005_kritenjob_extra_vars.py
kriten/migrations/0006_alter_kritenjob_name_alter_kritenjob_owner.py
kriten/migrations/0007_alter_kritenjob_stdout.py
kriten/migrations/0008_kritenrunner_alter_kritentask_runner.py
kriten/migrations/0009_kritenrunner_token.py
kriten/migrations/0010_alter_kritenjob_options_alter_kritencluster_name_and_more.py
kriten/migrations/__init__.py
kriten-0.1.0.dist-info/LICENSE
kriten-0.1.0.dist-info/METADATA
kriten-0.1.0.dist-info/WHEEL
kriten-0.1.0.dist-info/top_level.txt
kriten-0.1.0.dist-info/RECORD
